modulo/__init__.py
modulo/_base_client.py
modulo/_client.py
modulo/_constants.py
modulo/_exceptions.py
modulo/_models/__init__.py
modulo/_models/actions.py
modulo/_models/common.py
modulo/_models/integrations.py
modulo/_models/kits.py
modulo/_types.py
modulo/_version.py
modulo/base/__init__.py
modulo/base/actions.py
modulo/base/integrations.py
modulo/base/kits.py
modulo/models.py
modulo/py.typed
modulo_client-0.1.2.dist-info/METADATA
modulo_client-0.1.2.dist-info/WHEEL
modulo_client-0.1.2.dist-info/RECORD
