Metadata-Version: 2.4
Name: modulo-client
Version: 0.1.2
Summary: Python client for Modulo API with RSA signature authentication for LiveKit agent workers
License: MIT
Keywords: modulo,livekit,agent,api,client,tools,actions,integrations
Author: Modulo Team
Requires-Python: >=3.12,<3.14
Classifier: Development Status :: 4 - Beta
Classifier: Intended Audience :: Developers
Classifier: License :: OSI Approved :: MIT License
Classifier: Operating System :: OS Independent
Classifier: Programming Language :: Python :: 3
Classifier: Programming Language :: Python :: 3.12
Classifier: Programming Language :: Python :: 3.13
Classifier: Topic :: Software Development :: Libraries :: Python Modules
Classifier: Typing :: Typed
Requires-Dist: cryptography (>=41.0.0)
Requires-Dist: httpx (>=0.25.0)
Requires-Dist: typing_extensions (>=4.7.0)
Project-URL: Documentation, https://docs.modulo.so
Project-URL: Homepage, https://github.com/modulo-so/modulo-sdk
Project-URL: Repository, https://github.com/modulo-so/modulo-sdk
